tprof/__init__.py
tprof/__main__.py
tprof/api.py
tprof/main.py
tprof/py.typed
tprof/record.c
tprof/record.cp314t-win32.pyd
tprof/record.pyi
tprof-1.0.0.dist-info/licenses/LICENSE
tprof-1.0.0.dist-info/METADATA
tprof-1.0.0.dist-info/WHEEL
tprof-1.0.0.dist-info/entry_points.txt
tprof-1.0.0.dist-info/top_level.txt
tprof-1.0.0.dist-info/RECORD
